{
	"credit": "Made with Blockbench",
	"texture_size": [128, 128],
	"textures": {
		"0": "dwarfadventuremod:block/dwarf_anvil",
		"particle": "dwarfadventuremod:block/dwarf_anvil"
	},
	"elements": [
		{
			"from": [2, 6.4, 5.9],
			"to": [13.3, 9, 10.1],
			"rotation": {"angle": 0, "axis": "y", "origin": [8.575, 6.708, 8]},
			"faces": {
				"north": {"uv": [5.125, 7.375, 6.5, 7.75], "texture": "#0"},
				"east": {"uv": [8.375, 4.875, 8.875, 5.25], "texture": "#0"},
				"south": {"uv": [6.5, 7.375, 7.875, 7.75], "texture": "#0"},
				"west": {"uv": [8.375, 6, 8.875, 6.375], "texture": "#0"},
				"up": {"uv": [8, 3.625, 6.625, 3.125], "texture": "#0"},
				"down": {"uv": [8, 3.625, 6.625, 4.125], "texture": "#0"}
			}
		},
		{
			"from": [13.3, 7.1, 6.4],
			"to": [14.3, 9, 9.6],
			"rotation": {"angle": 0, "axis": "y", "origin": [8.575, 6.708, 8]},
			"faces": {
				"north": {"uv": [5.125, 6.75, 5.25, 7], "texture": "#0"},
				"east": {"uv": [8.625, 3.75, 9, 4], "texture": "#0"},
				"south": {"uv": [1, 7.5, 1.125, 7.75], "texture": "#0"},
				"west": {"uv": [8.625, 4, 9, 4.25], "texture": "#0"},
				"up": {"uv": [1.125, 7.5, 1, 7.125], "texture": "#0"},
				"down": {"uv": [4.375, 7.125, 4.25, 7.5], "texture": "#0"}
			}
		},
		{
			"from": [14.3, 7.8, 6.9],
			"to": [15.3, 8.8, 9.1],
			"rotation": {"angle": 0, "axis": "y", "origin": [8.575, 6.708, 8]},
			"faces": {
				"north": {"uv": [4.25, 7.5, 4.375, 7.625], "texture": "#0"},
				"east": {"uv": [6.625, 8.75, 6.875, 8.875], "texture": "#0"},
				"south": {"uv": [4.625, 8.875, 4.75, 9], "texture": "#0"},
				"west": {"uv": [6.875, 8.75, 7.125, 8.875], "texture": "#0"},
				"up": {"uv": [4.375, 8.5, 4.25, 8.25], "texture": "#0"},
				"down": {"uv": [7.25, 8.75, 7.125, 9], "texture": "#0"}
			}
		},
		{
			"from": [15.3, 8.2, 7.2],
			"to": [16, 8.8, 8.8],
			"rotation": {"angle": 0, "axis": "y", "origin": [8.575, 6.708, 8]},
			"faces": {
				"north": {"uv": [4.75, 8.875, 4.875, 9], "texture": "#0"},
				"east": {"uv": [7.25, 8.75, 7.5, 8.875], "texture": "#0"},
				"south": {"uv": [4.875, 8.875, 5, 9], "texture": "#0"},
				"west": {"uv": [7.5, 8.75, 7.75, 8.875], "texture": "#0"},
				"up": {"uv": [7.875, 9, 7.75, 8.75], "texture": "#0"},
				"down": {"uv": [8, 8.75, 7.875, 9], "texture": "#0"}
			}
		},
		{
			"from": [1, 8.1, 6.7],
			"to": [2, 9, 9.3],
			"rotation": {"angle": 0, "axis": "y", "origin": [8.575, 6.708, 8]},
			"faces": {
				"north": {"uv": [8.875, 4.875, 9, 5], "texture": "#0"},
				"east": {"uv": [6.75, 5.875, 7.125, 6], "texture": "#0"},
				"south": {"uv": [5, 8.875, 5.125, 9], "texture": "#0"},
				"west": {"uv": [8.75, 3.25, 9.125, 3.375], "texture": "#0"},
				"up": {"uv": [5.125, 8.875, 5, 8.5], "texture": "#0"},
				"down": {"uv": [5.25, 8.75, 5.125, 9.125], "texture": "#0"}
			}
		},
		{
			"from": [3, 7.4, 4.7],
			"to": [12.3, 9, 5.9],
			"rotation": {"angle": 0, "axis": "y", "origin": [8.575, 6.708, 8]},
			"faces": {
				"north": {"uv": [6.625, 5.25, 7.75, 5.5], "texture": "#0"},
				"east": {"uv": [8, 8.75, 8.125, 9], "texture": "#0"},
				"south": {"uv": [7.5, 6.75, 8.625, 7], "texture": "#0"},
				"west": {"uv": [8.75, 8.375, 8.875, 8.625], "texture": "#0"},
				"up": {"uv": [9.625, 0.875, 8.5, 0.75], "texture": "#0"},
				"down": {"uv": [9.625, 0.875, 8.5, 1], "texture": "#0"}
			}
		},
		{
			"from": [3, 7.4, 10.1],
			"to": [12.3, 9, 11.3],
			"rotation": {"angle": 0, "axis": "y", "origin": [8.575, 6.708, 8]},
			"faces": {
				"north": {"uv": [7.75, 5.25, 8.875, 5.5], "texture": "#0"},
				"east": {"uv": [8.75, 8.625, 8.875, 8.875], "texture": "#0"},
				"south": {"uv": [8, 3.5, 9.125, 3.75], "texture": "#0"},
				"west": {"uv": [0, 8.875, 0.125, 9.125], "texture": "#0"},
				"up": {"uv": [9.625, 7.5, 8.5, 7.375], "texture": "#0"},
				"down": {"uv": [9.625, 7.5, 8.5, 7.625], "texture": "#0"}
			}
		},
		{
			"from": [3.5, 8.1, 4],
			"to": [11.8, 8.7, 4.7],
			"rotation": {"angle": 0, "axis": "y", "origin": [8.575, 6.708, 8]},
			"faces": {
				"north": {"uv": [8.5, 8.125, 9.5, 8.25], "texture": "#0"},
				"east": {"uv": [8.875, 5, 9, 5.125], "texture": "#0"},
				"south": {"uv": [8.5, 8.25, 9.5, 8.375], "texture": "#0"},
				"west": {"uv": [8.875, 5.125, 9, 5.25], "texture": "#0"},
				"up": {"uv": [9.625, 1.125, 8.625, 1], "texture": "#0"},
				"down": {"uv": [9.625, 1.125, 8.625, 1.25], "texture": "#0"}
			}
		},
		{
			"from": [3.5, 8.1, 11.3],
			"to": [11.8, 8.7, 12],
			"rotation": {"angle": 0, "axis": "y", "origin": [8.575, 6.708, 8]},
			"faces": {
				"north": {"uv": [8.625, 1.25, 9.625, 1.375], "texture": "#0"},
				"east": {"uv": [5.25, 8.875, 5.375, 9], "texture": "#0"},
				"south": {"uv": [8.625, 1.375, 9.625, 1.5], "texture": "#0"},
				"west": {"uv": [8.875, 5.25, 9, 5.375], "texture": "#0"},
				"up": {"uv": [9.625, 1.625, 8.625, 1.5], "texture": "#0"},
				"down": {"uv": [9.625, 1.625, 8.625, 1.75], "texture": "#0"}
			}
		},
		{
			"from": [3.2, 1.9, 5.9],
			"to": [12.8, 2.4, 10.1],
			"rotation": {"angle": 0, "axis": "y", "origin": [8.575, 6.708, 8]},
			"faces": {
				"north": {"uv": [8.5, 0.5, 9.75, 0.625], "texture": "#0"},
				"east": {"uv": [6.25, 5.875, 6.75, 6], "texture": "#0"},
				"south": {"uv": [8.5, 0.625, 9.75, 0.75], "texture": "#0"},
				"west": {"uv": [8.625, 4.75, 9.125, 4.875], "texture": "#0"},
				"up": {"uv": [3.875, 7.625, 2.625, 7.125], "texture": "#0"},
				"down": {"uv": [8.375, 5.875, 7.125, 6.375], "texture": "#0"}
			}
		},
		{
			"from": [3.7, 2.4, 6.4],
			"to": [12.3, 2.9, 9.6],
			"rotation": {"angle": 0, "axis": "y", "origin": [8.575, 6.708, 8]},
			"faces": {
				"north": {"uv": [8.5, 7.625, 9.625, 7.75], "texture": "#0"},
				"east": {"uv": [8.75, 3.375, 9.125, 3.5], "texture": "#0"},
				"south": {"uv": [8.5, 7.75, 9.625, 7.875], "texture": "#0"},
				"west": {"uv": [5.25, 8.75, 5.625, 8.875], "texture": "#0"},
				"up": {"uv": [8.625, 1.375, 7.5, 1], "texture": "#0"},
				"down": {"uv": [8.625, 1.375, 7.5, 1.75], "texture": "#0"}
			}
		},
		{
			"from": [3.7, 5.9, 6.4],
			"to": [12.7, 6.4, 9.6],
			"rotation": {"angle": 0, "axis": "y", "origin": [8.575, 6.708, 8]},
			"faces": {
				"north": {"uv": [8.5, 7.875, 9.625, 8], "texture": "#0"},
				"east": {"uv": [8.75, 5.5, 9.125, 5.625], "texture": "#0"},
				"south": {"uv": [8.5, 8, 9.625, 8.125], "texture": "#0"},
				"west": {"uv": [5.625, 8.75, 6, 8.875], "texture": "#0"},
				"up": {"uv": [8.625, 6.75, 7.5, 6.375], "texture": "#0"},
				"down": {"uv": [3.75, 7.625, 2.625, 8], "texture": "#0"}
			}
		},
		{
			"from": [10.8, 4.4, 7.2],
			"to": [11.8, 6.4, 8.8],
			"rotation": {"angle": 0, "axis": "y", "origin": [8.575, 6.708, 8]},
			"faces": {
				"north": {"uv": [8.875, 0, 9, 0.25], "texture": "#0"},
				"east": {"uv": [8.75, 2.75, 9, 3], "texture": "#0"},
				"south": {"uv": [0.125, 8.875, 0.25, 9.125], "texture": "#0"},
				"west": {"uv": [8.75, 3, 9, 3.25], "texture": "#0"},
				"up": {"uv": [0.375, 9.125, 0.25, 8.875], "texture": "#0"},
				"down": {"uv": [9, 0.25, 8.875, 0.5], "texture": "#0"}
			}
		},
		{
			"from": [11.8, 5.4, 7.5],
			"to": [12.3, 6.4, 8.5],
			"rotation": {"angle": 0, "axis": "y", "origin": [8.575, 6.708, 8]},
			"faces": {
				"north": {"uv": [8.875, 1.75, 9.125, 1.875], "texture": "#0"},
				"east": {"uv": [5.375, 8.875, 5.5, 9], "texture": "#0"},
				"south": {"uv": [8.875, 1.875, 9.125, 2], "texture": "#0"},
				"west": {"uv": [8.875, 5.375, 9, 5.5], "texture": "#0"},
				"up": {"uv": [9.125, 2.125, 8.875, 2], "texture": "#0"},
				"down": {"uv": [9.125, 2.125, 8.875, 2.25], "texture": "#0"}
			}
		},
		{
			"from": [4.2, 2.9, 6.9],
			"to": [8.8, 5.9, 9.1],
			"rotation": {"angle": 0, "axis": "y", "origin": [8.575, 6.708, 8]},
			"faces": {
				"north": {"uv": [8, 3.75, 8.375, 4.125], "texture": "#0"},
				"east": {"uv": [7.875, 7.375, 8.125, 7.75], "texture": "#0"},
				"south": {"uv": [2.25, 8.5, 2.625, 8.875], "texture": "#0"},
				"west": {"uv": [8.125, 5.5, 8.375, 5.875], "texture": "#0"},
				"up": {"uv": [9, 4.5, 8.625, 4.25], "texture": "#0"},
				"down": {"uv": [9, 4.5, 8.625, 4.75], "texture": "#0"}
			}
		},
		{
			"from": [8.2, 2.9, 6.9],
			"to": [10.8, 5.9, 9.1],
			"rotation": {"angle": 0, "axis": "y", "origin": [8.575, 6.708, 8]},
			"faces": {
				"north": {"uv": [4.25, 8.5, 4.625, 8.875], "texture": "#0"},
				"east": {"uv": [8.625, 6.375, 8.875, 6.75], "texture": "#0"},
				"south": {"uv": [4.625, 8.5, 5, 8.875], "texture": "#0"},
				"west": {"uv": [8.625, 6.75, 8.875, 7.125], "texture": "#0"},
				"up": {"uv": [9, 7.375, 8.625, 7.125], "texture": "#0"},
				"down": {"uv": [0.75, 8.75, 0.375, 9], "texture": "#0"}
			}
		},
		{
			"from": [10.3, 0, 3.4],
			"to": [12.7, 1.6, 12.6],
			"rotation": {"angle": 0, "axis": "y", "origin": [8.575, 6.708, 8]},
			"faces": {
				"north": {"uv": [7.75, 2.5, 8, 3.125], "texture": "#0"},
				"east": {"uv": [5.25, 6.375, 6.375, 7], "texture": "#0"},
				"south": {"uv": [1.5, 8.5, 1.75, 9.125], "texture": "#0"},
				"west": {"uv": [6.375, 6.375, 7.5, 7], "texture": "#0"},
				"up": {"uv": [4, 9.375, 3.75, 8.25], "texture": "#0"},
				"down": {"uv": [4.25, 8.25, 4, 9.375], "texture": "#0"}
			}
		},
		{
			"from": [3.3, 0, 3.4],
			"to": [5.7, 1.6, 12.6],
			"rotation": {"angle": 0, "axis": "y", "origin": [8.575, 6.708, 8]},
			"faces": {
				"north": {"uv": [1.75, 8.5, 2, 9.125], "texture": "#0"},
				"east": {"uv": [0, 6.5, 1.125, 7.125], "texture": "#0"},
				"south": {"uv": [2, 8.5, 2.25, 9.125], "texture": "#0"},
				"west": {"uv": [6.625, 2.5, 7.75, 3.125], "texture": "#0"},
				"up": {"uv": [8.625, 4.875, 8.375, 3.75], "texture": "#0"},
				"down": {"uv": [8.375, 8.375, 8.125, 9.5], "texture": "#0"}
			}
		},
		{
			"from": [2.7, 0, 5.4],
			"to": [13.3, 1.9, 10.6],
			"rotation": {"angle": 0, "axis": "y", "origin": [8.575, 6.708, 8]},
			"faces": {
				"north": {"uv": [5.25, 2.5, 6.625, 3.125], "texture": "#0"},
				"east": {"uv": [0.375, 7.125, 1, 7.75], "texture": "#0"},
				"south": {"uv": [5.25, 3.125, 6.625, 3.75], "texture": "#0"},
				"west": {"uv": [3.75, 7.625, 4.375, 8.25], "texture": "#0"},
				"up": {"uv": [6.625, 4.375, 5.25, 3.75], "texture": "#0"},
				"down": {"uv": [6.625, 4.375, 5.25, 5], "texture": "#0"}
			}
		},
		{
			"from": [3.55714, 9.06599, 8.32933],
			"to": [6.55714, 10.56599, 9.32933],
			"rotation": {"angle": -45, "axis": "y", "origin": [8.575, 6.708, 8]},
			"faces": {
				"north": {"uv": [9.125, 2.5, 8.75, 2.75], "rotation": 180, "texture": "#0"},
				"east": {"uv": [2.25, 8.875, 2.5, 9], "rotation": 270, "texture": "#0"},
				"south": {"uv": [1.125, 9, 0.75, 8.75], "texture": "#0"},
				"west": {"uv": [8.875, 2.25, 9.125, 2.375], "rotation": 90, "texture": "#0"},
				"up": {"uv": [8.75, 5.625, 9.125, 5.75], "rotation": 180, "texture": "#0"},
				"down": {"uv": [8.75, 5.75, 9.125, 5.875], "texture": "#0"}
			}
		},
		{
			"from": [4.75714, 10.56599, 8.62933],
			"to": [5.35714, 13.56599, 9.02933],
			"rotation": {"angle": -45, "axis": "y", "origin": [8.575, 6.708, 8]},
			"faces": {
				"north": {"uv": [6.625, 8.75, 6.5, 9.125], "rotation": 180, "texture": "#0"},
				"east": {"uv": [8.75, 5.875, 9.125, 6], "rotation": 270, "texture": "#0"},
				"south": {"uv": [6.5, 9.125, 6.375, 8.75], "texture": "#0"},
				"west": {"uv": [6, 8.75, 6.375, 8.875], "rotation": 90, "texture": "#0"},
				"up": {"uv": [5.5, 8.875, 5.625, 9], "rotation": 180, "texture": "#0"},
				"down": {"uv": [5.625, 8.875, 5.75, 9], "texture": "#0"}
			}
		},
		{
			"from": [4.65714, 11.56599, 8.52933],
			"to": [5.45714, 13.66599, 9.12933],
			"rotation": {"angle": -45, "axis": "y", "origin": [8.575, 6.708, 8]},
			"faces": {
				"north": {"uv": [4.625, 8.875, 4.5, 9.125], "rotation": 180, "texture": "#0"},
				"east": {"uv": [8.875, 2.375, 9.125, 2.5], "rotation": 270, "texture": "#0"},
				"south": {"uv": [2.625, 9.125, 2.5, 8.875], "texture": "#0"},
				"west": {"uv": [4.25, 8.875, 4.5, 9], "rotation": 90, "texture": "#0"},
				"up": {"uv": [5.75, 8.875, 5.875, 9], "rotation": 180, "texture": "#0"},
				"down": {"uv": [5.875, 8.875, 6, 9], "texture": "#0"}
			}
		}
	],
	"display": {
		"thirdperson_righthand": {
			"rotation": [0, -90, 0],
			"scale": [0.5, 0.5, 0.5]
		},
		"thirdperson_lefthand": {
			"rotation": [0, 90, 0],
			"scale": [0.5, 0.5, 0.5]
		},
		"firstperson_righthand": {
			"translation": [0.25, 2, -0.5],
			"scale": [0.5, 0.5, 0.5]
		},
		"firstperson_lefthand": {
			"rotation": [0, -180, 0],
			"translation": [-0.25, 1.5, -1],
			"scale": [0.5, 0.5, 0.5]
		},
		"ground": {
			"translation": [0, 3.75, 0],
			"scale": [0.75, 0.75, 0.75]
		},
		"gui": {
			"rotation": [28, 43, 19],
			"translation": [-0.75, 2, 0],
			"scale": [0.88, 0.88, 0.88]
		},
		"head": {
			"translation": [0, 13, 0],
			"scale": [0.87, 0.87, 0.87]
		},
		"fixed": {
			"rotation": [-31, 0, 0],
			"translation": [-0.25, 2, -2.75]
		}
	},
	"groups": [
		{
			"name": "Dwarf Anvil",
			"origin": [8, 8, 8],
			"color": 0,
			"children": [
				{
					"name": "Anvil",
					"origin": [8, 8, 8],
					"color": 0,
					"children": [
						{
							"name": "Anvil Plate",
							"origin": [7, 7, 4],
							"color": 0,
							"children": [0, 1, 2, 3, 4, 5, 6, 7, 8]
						},
						{
							"name": "Anvil Neck",
							"origin": [7, 5, 4],
							"color": 0,
							"children": [9, 10, 11, 12, 13, 14, 15]
						},
						{
							"name": "Anvil Leg",
							"origin": [6.4, 5.15, 8],
							"color": 0,
							"children": [16, 17, 18]
						}
					]
				},
				{
					"name": "Hammer",
					"origin": [8, 8, 8],
					"color": 0,
					"children": [19, 20, 21]
				}
			]
		}
	]
}