{
  "parent": "minecraft:recipes/root",
  "criteria": {
    "has_tera_block": {
      "conditions": {
        "items": [
          {
            "items": [
              "dwarfadventuremod:tera_block"
            ]
          }
        ]
      },
      "trigger": "minecraft:inventory_changed"
    },
    "has_the_recipe": {
      "conditions": {
        "recipe": "minecraft:tera_spirit_ingot_from_tera_block"
      },
      "trigger": "minecraft:recipe_unlocked"
    }
  },
  "requirements": [
    [
      "has_tera_block",
      "has_the_recipe"
    ]
  ],
  "rewards": {
    "recipes": [
      "minecraft:tera_spirit_ingot_from_tera_block"
    ]
  },
  "sends_telemetry_event": false
}